interplanetary_invaders/__init__.py
interplanetary_invaders/__main__.py
interplanetary_invaders/icon.png
interplanetary_invaders/logo.png
interplanetary_invaders/main.py
interplanetary_invaders/audio/alienDie.wav
interplanetary_invaders/audio/alienDie2.wav
interplanetary_invaders/audio/alienDie3.wav
interplanetary_invaders/audio/alienDie3_old.wav
interplanetary_invaders/audio/alienDrop1.wav
interplanetary_invaders/audio/alienDrop2.wav
interplanetary_invaders/audio/alienDrop3.wav
interplanetary_invaders/audio/alienExplode.wav
interplanetary_invaders/audio/alienExplode2.wav
interplanetary_invaders/audio/alienExplode3.wav
interplanetary_invaders/audio/alienHit.wav
interplanetary_invaders/audio/alienLaser-old.wav
interplanetary_invaders/audio/alienLaser.wav
interplanetary_invaders/audio/cashRegister.wav
interplanetary_invaders/audio/click.wav
interplanetary_invaders/audio/collectMoney.wav
interplanetary_invaders/audio/donk.wav
interplanetary_invaders/audio/error.wav
interplanetary_invaders/audio/flak.wav
interplanetary_invaders/audio/flak_old.wav
interplanetary_invaders/audio/greenAlienImpact.wav
interplanetary_invaders/audio/greenlaser-old.wav
interplanetary_invaders/audio/greenlaser.wav
interplanetary_invaders/audio/heart.wav
interplanetary_invaders/audio/item-old1.wav
interplanetary_invaders/audio/item.wav
interplanetary_invaders/audio/jet.wav
interplanetary_invaders/audio/jupiter_hover_explode.wav
interplanetary_invaders/audio/laser-old1.wav
interplanetary_invaders/audio/laser.wav
interplanetary_invaders/audio/lightning.wav
interplanetary_invaders/audio/lightning2.wav
interplanetary_invaders/audio/magnetLoop.wav
interplanetary_invaders/audio/money.wav
interplanetary_invaders/audio/purchase.wav
interplanetary_invaders/audio/purpleAlienDie.wav
interplanetary_invaders/audio/shield.wav
interplanetary_invaders/audio/slowDown.wav
interplanetary_invaders/audio/speedUp.wav
interplanetary_invaders/audio/takeDamage.wav
interplanetary_invaders/audio/yellowAlienDie.wav
Interplanetary_Invaders-0.7.dist-info/LICENSE
Interplanetary_Invaders-0.7.dist-info/METADATA
Interplanetary_Invaders-0.7.dist-info/WHEEL
Interplanetary_Invaders-0.7.dist-info/entry_points.txt
Interplanetary_Invaders-0.7.dist-info/top_level.txt
Interplanetary_Invaders-0.7.dist-info/RECORD
