Metadata-Version: 2.1
Name: Interplanetary-Invaders
Version: 0.7
Summary: Space-invaders-esc game where you battle alien spiders across the solar system
Home-page: https://github.com/nachomonkey/interplanetary-invaders
Author: NachoMonkey
Classifier: Operating System :: OS Independent
Requires-Python: >=3.7
License-File: LICENSE
Requires-Dist: setuptools
Requires-Dist: pygame (>=1.9.6)
Requires-Dist: humanize (>=0.5.0)
